geohmt/__init__.py
geohmt/geohmt.py
geoHMT-0.0.5.dist-info/LICENSE
geoHMT-0.0.5.dist-info/METADATA
geoHMT-0.0.5.dist-info/WHEEL
geoHMT-0.0.5.dist-info/top_level.txt
geoHMT-0.0.5.dist-info/RECORD
