Metadata-Version: 2.1
Name: geoHMT
Version: 0.0.5
Summary: A python package for interactive modelling for MDHM
Home-page: https://github.com/drunk-bird/geoHMT
Author: drunkbear
Author-email: drarnol94@gmail.com
License: MIT license
Keywords: geohmt
Classifier: Development Status :: 2 - Pre-Alpha
Classifier: Intended Audience :: Developers
Classifier: License :: OSI Approved :: MIT License
Classifier: Natural Language :: English
Classifier: Programming Language :: Python :: 3
Classifier: Programming Language :: Python :: 3.7
Classifier: Programming Language :: Python :: 3.8
Classifier: Programming Language :: Python :: 3.9
Classifier: Programming Language :: Python :: 3.10
Requires-Python: >=3.7
License-File: LICENSE
